[
  {
    "constant": true,
    "inputs": [],
    "name": "tokensUnlockAt",
    "outputs": [
      {
        "name": "",
        "type": "uint256"
      }
    ],
    "payable": false,
    "stateMutability": "view",
    "type": "function"
  },
  {
    "constant": true,
    "inputs": [],
    "name": "_status",
    "outputs": [
      {
        "name": "",
        "type": "uint8"
      }
    ],
    "payable": false,
    "stateMutability": "view",
    "type": "function"
  },
  {
    "constant": true,
    "inputs": [],
    "name": "accountAddress",
    "outputs": [
      {
        "name": "",
        "type": "address"
      }
    ],
    "payable": false,
    "stateMutability": "view",
    "type": "function"
  },
  {
    "constant": false,
    "inputs": [],
    "name": "renounceOwnership",
    "outputs": [],
    "payable": false,
    "stateMutability": "nonpayable",
    "type": "function"
  },
  {
    "constant": true,
    "inputs": [],
    "name": "verifiedAt",
    "outputs": [
      {
        "name": "",
        "type": "uint256"
      }
    ],
    "payable": false,
    "stateMutability": "view",
    "type": "function"
  },
  {
    "constant": true,
    "inputs": [],
    "name": "owner",
    "outputs": [
      {
        "name": "",
        "type": "address"
      }
    ],
    "payable": false,
    "stateMutability": "view",
    "type": "function"
  },
  {
    "constant": true,
    "inputs": [],
    "name": "accountFieldName",
    "outputs": [
      {
        "name": "",
        "type": "string"
      }
    ],
    "payable": false,
    "stateMutability": "view",
    "type": "function"
  },
  {
    "constant": true,
    "inputs": [],
    "name": "coOwner",
    "outputs": [
      {
        "name": "",
        "type": "address"
      }
    ],
    "payable": false,
    "stateMutability": "view",
    "type": "function"
  },
  {
    "constant": false,
    "inputs": [
      {
        "name": "newOwner",
        "type": "address"
      }
    ],
    "name": "transferOwnership",
    "outputs": [],
    "payable": false,
    "stateMutability": "nonpayable",
    "type": "function"
  },
  {
    "constant": true,
    "inputs": [],
    "name": "dataIndex",
    "outputs": [
      {
        "name": "",
        "type": "uint256"
      }
    ],
    "payable": false,
    "stateMutability": "view",
    "type": "function"
  },
  {
    "constant": true,
    "inputs": [],
    "name": "rewardAmount",
    "outputs": [
      {
        "name": "",
        "type": "uint256"
      }
    ],
    "payable": false,
    "stateMutability": "view",
    "type": "function"
  },
  {
    "inputs": [
      {
        "name": "contextStorage",
        "type": "address"
      },
      {
        "name": "reward",
        "type": "uint256"
      },
      {
        "name": "account",
        "type": "address"
      },
      {
        "name": "coOwnerAddress",
        "type": "address"
      },
      {
        "name": "index",
        "type": "uint256"
      },
      {
        "name": "fieldName",
        "type": "string"
      }
    ],
    "payable": false,
    "stateMutability": "nonpayable",
    "type": "constructor"
  },
  {
    "anonymous": false,
    "inputs": [
      {
        "indexed": true,
        "name": "previousOwner",
        "type": "address"
      }
    ],
    "name": "OwnershipRenounced",
    "type": "event"
  },
  {
    "anonymous": false,
    "inputs": [
      {
        "indexed": true,
        "name": "previousOwner",
        "type": "address"
      },
      {
        "indexed": true,
        "name": "newOwner",
        "type": "address"
      }
    ],
    "name": "OwnershipTransferred",
    "type": "event"
  },
  {
    "constant": false,
    "inputs": [
      {
        "name": "verificationResult",
        "type": "bool"
      }
    ],
    "name": "finalizeVerification",
    "outputs": [],
    "payable": false,
    "stateMutability": "nonpayable",
    "type": "function"
  },
  {
    "constant": true,
    "inputs": [],
    "name": "getData",
    "outputs": [
      {
        "name": "data",
        "type": "string"
      }
    ],
    "payable": false,
    "stateMutability": "view",
    "type": "function"
  },
  {
    "constant": false,
    "inputs": [],
    "name": "withdraw",
    "outputs": [],
    "payable": false,
    "stateMutability": "nonpayable",
    "type": "function"
  },
  {
    "constant": true,
    "inputs": [],
    "name": "getStatus",
    "outputs": [
      {
        "name": "",
        "type": "uint8"
      }
    ],
    "payable": false,
    "stateMutability": "view",
    "type": "function"
  },
  {
    "constant": true,
    "inputs": [],
    "name": "getStatusName",
    "outputs": [
      {
        "name": "",
        "type": "string"
      }
    ],
    "payable": false,
    "stateMutability": "view",
    "type": "function"
  }
]